shumway/__init__.py
test/__init__.py
test/metrics_test.py
shumway-4.0.0.dist-info/LICENSE
shumway-4.0.0.dist-info/METADATA
shumway-4.0.0.dist-info/WHEEL
shumway-4.0.0.dist-info/top_level.txt
shumway-4.0.0.dist-info/RECORD
