Metadata-Version: 2.1
Name: shumway
Version: 4.0.0
Summary: Micro metrics library for ffwd
Home-page: https://github.com/spotify/shumway
Author: Lynn Root
Author-email: lynn@spotify.com
Maintainer: Lynn Root
Maintainer-email: lynn@spotify.com
License: Apache 2.0
Keywords: metrics,ffwd,heroic
Classifier: Development Status :: 5 - Production/Stable
Classifier: License :: OSI Approved :: Apache Software License
Classifier: Natural Language :: English
Classifier: Operating System :: POSIX :: Linux
Classifier: Operating System :: MacOS :: MacOS X
Classifier: Programming Language :: Python
Classifier: Programming Language :: Python :: 3
Classifier: Programming Language :: Python :: 3.7
Classifier: Programming Language :: Python :: 3.8
Classifier: Programming Language :: Python :: Implementation :: CPython
Classifier: Programming Language :: Python :: Implementation :: PyPy
Classifier: Topic :: Software Development :: Libraries :: Python Modules
License-File: LICENSE
Requires-Dist: requests
Requires-Dist: six
